Analysis/Linear_Corr.py
Analysis/__init__.py
Linear_Correlation-0.2.5.dist-info/METADATA
Linear_Correlation-0.2.5.dist-info/WHEEL
Linear_Correlation-0.2.5.dist-info/top_level.txt
Linear_Correlation-0.2.5.dist-info/RECORD
